[
    {
      "title": "Field update: coastal plantings completed",
      "excerpt": "Volunteers finished the last dune section this week.",
      "date": "2025-10-10",
      "url": "#"
    },
    {
      "title": "Workshop notes published",
      "excerpt": "Slides and a short summary are now available.",
      "date": "2025-10-14",
      "url": "#"
    },
    {
      "title": "New partner joins pilot",
      "excerpt": "Welcome to the collaboration.",
      "date": "2025-10-18",
      "url": "#"
    }
  ]
  